orion/algo/robo/__init__.py
orion/algo/robo/_version.py
orion/algo/robo/base.py
orion/algo/robo/bohamiann.py
orion/algo/robo/dngo.py
orion/algo/robo/gp.py
orion/algo/robo/randomforest.py
orion.algo.robo-0.1.1.dist-info/LICENSE
orion.algo.robo-0.1.1.dist-info/METADATA
orion.algo.robo-0.1.1.dist-info/WHEEL
orion.algo.robo-0.1.1.dist-info/entry_points.txt
orion.algo.robo-0.1.1.dist-info/top_level.txt
orion.algo.robo-0.1.1.dist-info/RECORD
