Metadata-Version: 2.1
Name: orion.algo.robo
Version: 0.1.1
Summary: TODO
Home-page: https://github.com/Epistimio/orion.algo.robo
Author: Epistímio
Author-email: xavier.bouthillier@umontreal.ca
License: BSD-3-Clause
Keywords: Machine Learning,Deep Learning,Distributed,Optimization
Platform: Linux
Classifier: Development Status :: 1 - Planning
Classifier: Intended Audience :: Developers
Classifier: Intended Audience :: Education
Classifier: Intended Audience :: Science/Research
Classifier: License :: OSI Approved :: BSD License
Classifier: Operating System :: POSIX
Classifier: Operating System :: Unix
Classifier: Programming Language :: Python
Classifier: Topic :: Scientific/Engineering
Classifier: Programming Language :: Python :: 3
Classifier: Programming Language :: Python :: 3.6
Classifier: Programming Language :: Python :: 3.7
Classifier: Programming Language :: Python :: 3.8
Classifier: Programming Language :: Python :: 3.9
License-File: LICENSE
Requires-Dist: orion (>=0.1.11)
Requires-Dist: numpy
Requires-Dist: torch (>=1.2.0)
Provides-Extra: test
Requires-Dist: pytest (>=3.0.0) ; extra == 'test'
